setup.py
distributions_test_RCR/Binomialdistribution.py
distributions_test_RCR/Binomialdistribution_challenge.py
distributions_test_RCR/Gaussiandistribution.py
distributions_test_RCR/Generaldistribution.py
distributions_test_RCR/__init__.py
distributions_test_RCR.egg-info/PKG-INFO
distributions_test_RCR.egg-info/SOURCES.txt
distributions_test_RCR.egg-info/dependency_links.txt
distributions_test_RCR.egg-info/not-zip-safe
distributions_test_RCR.egg-info/top_level.txt