Metadata-Version: 1.0
Name: distributions-test-RCR
Version: 0.1
Summary: Gaussian distributions, binomial distributions
Home-page: UNKNOWN
Author: UNKNOWN
Author-email: UNKNOWN
License: UNKNOWN
Platform: UNKNOWN
